my_packageDRS/__init__.py
my_packageDRS/model.py
my_packageDRS/analysis/__init__.py
my_packageDRS/analysis/visualize.py
my_packageDRS/data/__init__.py
my_packageDRS/data/dataset.py
my_packageDRS/data/transform/__init__.py
my_packageDRS/data/transform/blur.py
my_packageDRS/data/transform/crop.py
my_packageDRS/data/transform/flip.py
my_packageDRS/data/transform/rescaleimage.py
my_packageDRS/data/transform/rotate.py
my_packageDRS-0.2.dist-info/LICENSE.txt
my_packageDRS-0.2.dist-info/METADATA
my_packageDRS-0.2.dist-info/WHEEL
my_packageDRS-0.2.dist-info/top_level.txt
my_packageDRS-0.2.dist-info/RECORD
